optiz/__init__.py
optiz/constants.py
optiz/input.py
optiz/pipeline.py
optiz/utils.py
optiz/models/__init__.py
optiz/models/cp_model.py
optiz-0.0.7.dist-info/LICENSE.txt
optiz-0.0.7.dist-info/METADATA
optiz-0.0.7.dist-info/WHEEL
optiz-0.0.7.dist-info/top_level.txt
optiz-0.0.7.dist-info/RECORD
