Metadata-Version: 2.1
Name: optiz
Version: 0.0.7
Summary: Optimization library for Python
Home-page: https://github.com/lucasmrdt/optiz
Author: Lucas Marandat
Author-email: lucas.mrdt@gmail.com
License: MIT
Keywords: optimisation
Platform: UNKNOWN
Classifier: Development Status :: 3 - Alpha
Classifier: Intended Audience :: Developers
Classifier: Topic :: Software Development :: Build Tools
Classifier: License :: OSI Approved :: MIT License
Classifier: Programming Language :: Python :: 3
Classifier: Programming Language :: Python :: 3.4
Classifier: Programming Language :: Python :: 3.5
Classifier: Programming Language :: Python :: 3.6
Classifier: Programming Language :: Python :: 3.7
Requires-Dist: ortools (==9.2.9972)
